ossrfc/__init__.py
ossrfc/_analysis.py
ossrfc/_contributions.py
ossrfc/_git.py
ossrfc/_licensing.py
ossrfc/_matching.py
ossrfc/_report.py
ossrfc/checker.py
oss_red_flag_checker-0.1.7.dist-info/LICENSE.txt
oss_red_flag_checker-0.1.7.dist-info/LICENSES/Apache-2.0.txt
oss_red_flag_checker-0.1.7.dist-info/METADATA
oss_red_flag_checker-0.1.7.dist-info/WHEEL
oss_red_flag_checker-0.1.7.dist-info/entry_points.txt
oss_red_flag_checker-0.1.7.dist-info/RECORD
