Metadata-Version: 2.3
Name: oss-red-flag-checker
Version: 0.1.7
Summary: Check remote repositories for typical red flags like CLAs and risks due to low development activity
License: Apache-2.0
Keywords: ospo,open-source-management,supply-chain,risk-analysis
Author: Open Source at Deutsche Bahn
Author-email: opensource@deutschebahn.com
Maintainer: Max Mehl
Maintainer-email: max.mehl@deutschebahn.com
Requires-Python: >=3.9,<4.0
Classifier: Intended Audience :: Information Technology
Classifier: License :: OSI Approved :: Apache Software License
Classifier: Programming Language :: Python :: 3
Classifier: Programming Language :: Python :: 3.9
Classifier: Programming Language :: Python :: 3.10
Classifier: Programming Language :: Python :: 3.11
Classifier: Programming Language :: Python :: 3.12
Classifier: Programming Language :: Python :: 3.13
Classifier: Topic :: Software Development
Requires-Dist: gitpython (>=3.1.44,<4.0.0)
Requires-Dist: platformdirs (>=4.3.8,<5.0.0)
Requires-Dist: pygithub (>=2.6.1,<3.0.0)
Requires-Dist: termcolor (>=3.1.0,<4.0.0)
Requires-Dist: tqdm (>=4.67.1,<5.0.0)
Project-URL: Repository, https://github.com/dbsystel/oss-red-flag-checker/
